CHANGES.txt
README.txt
bootstrap.py
buildout.cfg
setup.py
src/zope/__init__.py
src/zope.app.sqlexpr.egg-info/PKG-INFO
src/zope.app.sqlexpr.egg-info/SOURCES.txt
src/zope.app.sqlexpr.egg-info/dependency_links.txt
src/zope.app.sqlexpr.egg-info/namespace_packages.txt
src/zope.app.sqlexpr.egg-info/not-zip-safe
src/zope.app.sqlexpr.egg-info/requires.txt
src/zope.app.sqlexpr.egg-info/top_level.txt
src/zope/app/__init__.py
src/zope/app/sqlexpr/MAINTAINER.txt
src/zope/app/sqlexpr/README.txt
src/zope/app/sqlexpr/SETUP.cfg
src/zope/app/sqlexpr/TODO.txt
src/zope/app/sqlexpr/VERSION.txt
src/zope/app/sqlexpr/__init__.py
src/zope/app/sqlexpr/configure.zcml
src/zope/app/sqlexpr/sqlexpr.py
src/zope/app/sqlexpr/tests.py
src/zope/app/sqlexpr/zope.app.sqlexpr-configure.zcml